soccerdata/__init__.py
soccerdata/_common.py
soccerdata/_config.py
soccerdata/clubelo.py
soccerdata/espn.py
soccerdata/fbref.py
soccerdata/fivethirtyeight.py
soccerdata/match_history.py
soccerdata/sofifa.py
soccerdata/whoscored.py
j_owens_soccerdata-0.0.2.dev1644950218.dist-info/LICENSE.rst
j_owens_soccerdata-0.0.2.dev1644950218.dist-info/WHEEL
j_owens_soccerdata-0.0.2.dev1644950218.dist-info/METADATA
j_owens_soccerdata-0.0.2.dev1644950218.dist-info/RECORD
