Metadata-Version: 2.1
Name: j-owens-soccerdata
Version: 0.0.2.dev1644950218
Summary: A collection of wrappers over soccer data from various websites / APIs. Modified to not fail on parsing unplaying games.
Home-page: https://github.com/probberechts/soccerdata
License: Apache-2.0
Keywords: soccer,football,soccer data,web scraping,soccer analytics
Author: Pieter Robberechts
Author-email: pieter.robberechts@kuleuven.be
Requires-Python: >=3.7,<4.0.0
Classifier: License :: OSI Approved :: Apache Software License
Classifier: License :: OSI Approved :: MIT License
Classifier: Operating System :: OS Independent
Classifier: Programming Language :: Python :: 3
Classifier: Programming Language :: Python :: 3.10
Classifier: Programming Language :: Python :: 3.7
Classifier: Programming Language :: Python :: 3.8
Classifier: Programming Language :: Python :: 3.9
Requires-Dist: PySocks (>=1.7.1,<2.0.0)
Requires-Dist: Unidecode (>=1.2.0,<2.0.0)
Requires-Dist: fake_useragent (>=0.1.11,<0.2.0)
Requires-Dist: html5lib (>=1.1,<2.0)
Requires-Dist: lxml (>=4.6,<5.0)
Requires-Dist: pandas (>=1.0,<2.0)
Requires-Dist: pretty-errors (>=1.2.25,<2.0.0)
Requires-Dist: requests (>=2.23,<3.0)
Requires-Dist: rich (>=11.0.0,<12.0.0)
Requires-Dist: selenium (>=4.0.0,<5.0.0)
Requires-Dist: undetected-chromedriver (>=3.1.3,<4.0.0)
Requires-Dist: unicode (>=2.7,<3.0)
Project-URL: Repository, https://github.com/J-Owens/soccerdata
